[
  {
    "company": "Standard Poors Moody’s Fitch",
    "description": "İlk olarak New York’ta yaşayan bir manifaturacının sadece kendi yaptığı işi değerlendirmesiyle ortaya çıkan kredi derecelendirme işlemi, 1837 yılında Amerika ekonomisinde yaşanan finansal kriz sonucunda Amerikan Şirketleri’ne olan güvenin sarsılmasıyla mali aktörler tarafından talep görmeye başlamıştır. Derecelendirme işleminin çok kısa bir sürede önem kazanması sonucunda, günümüzde de halen ekonomide büyük bir öneme sahip olan dört büyük uluslararası kredi derecelendirme kuruluşundan ilk üçü Amerikan merkezli olan, Moody’s, Standard and Poor’s ve Fitch kurulmuştur. 1985 yılına gelindiğinde ise diğer bir derecelendirme kuruluşu olan Japanese Credit Rating (JCR) faaliyete geçmiştir.Uzun yıllar sadece ortaya çıktıkları ülkelerde yoğun talep ile karşılanan kredi derecelendirme kuruluşları, 1990’lı yıllardan sonra küreselleşmenin artmasıyla birlikte uluslararası statü kazanmıştır.Merkezi Amerika’da olan Standard & Poors(S&P) kredi derecelendirme kuruluşu, firmaları ve ülkeleri değerlendirmeye tabi tutar. Ülkelere borç vermek isteyen yatırımcılar, ülkelerin kredi değerliliğine göre önerilen faizleri değerlendirmeye alır. Bu kredi değerlendirmeleri S&P gibi kredi derecelendirme kuruluşlarının verdiği derecelendirme puanlarıyla belirlenmektedir.Kredi değerliliği yüksek olan ülkelerin borçlanmalarının maliyeti daha düşük olmaktadır.Dış finansman açığı yüksek olan Türkiye ekonomisinin ihtiyaç duyduğu yabancı kurumsal fonların bir bölümüne, üç kredi derecelendirme kuruluşunun en az ikisinden yatırım yapılabilir notu alması gerekiyor. Yabancı ülke yatırımcıları buna göre yatırımları değerlendiriyor.Türkiye, Merkezi Amerika’da olan Moody’s ve Fitch Ratings kredi derecelendirme kuruluşlarından yatırım yapılabilir düzeyde kredi notu almış durumda ancak darbe teşebbüsü sonrası Moody’s kredi derecelendirme kuruluşunun Türkiye kredi notunu yatırım yapılabilir en düşük düzey olan Baa3 seviyesinde tuttuğunu ve görünümünün negatifte olduğunu açıklarken, bir kaç ay içinde yeni değerlendirme yapılacağı belirtildi. Türkiye’ye yatırım için geçerli notu vermeyen S&P ise Türkiye’nin BB+ olan notunu BB’ye düşürerek durağan olan kredi notu görünümünü negatif olarak belirledi.S&P ve Fitch Kredi Derecelendirme Notları:Yatırım dereceleriAAA: En yüksek kalite, sağlamAA+, Aa, AA-: En yüksek dereceden düşük bir farklılığa sahip olmakla birlikte, yine yüksek dereceli ve sağlamdır.A+,A: Ortanın üstündedir. Sağlam ve güvenilir olmakla birlikte ekonomik şartlardan etkilenebilir.BBB+,BBB,BBB-: Orta derecelidir. Uzun vadede risklidir. değişebilir özellikler taşır.Spekülatif DereceleriBB+,BB,BB- : Değişebilir özelliktedir, belirsizlikler taşır.B+,B,B- : Yatırım niteliği taşımaz. Borçlanma şartlarına uymama ihtimali yüksektir.CCC+,CCC,CCC- : Kısa dönemli riski dahi oldukça yüksektir.CC : Tamamen spekülatiftir. Geri ödeme hemen hemen imkânsızdır.C : En düşük kalite, En yüksek riskMoody’s derecelendirme sistemide benzer şekilde en iyiden en kötüye şöyle sıralanır:Yatırım dereceleriAAA, Aa1, Aa2, Aa3, A1, A2, A3, Baa1, Baa2, Baa3Spekülatif DereceleriBa1, Ba2, Ba3, B1, B2, B3, Caa1, Caa2, Caa3, Ca, C",
    "documents": [
      "CE"
    ],
    "parent": null,
    "origin": "US",
    "updated_date": "2018-08-26",
    "domain": "spglobal.com, moodys.com, fitchratings.com"
  },
  {
    "company": "Keter",
    "description": "Keter Plastik1948 yılında Joseph Sagol tarafından kurulmuş olan Keter Group bünyesinde üretilen plastik ürünler markasıdır.Dış mekan mobilyaları, ev depolama ve organizasyon ürünleri üretmektedir.Keter Group hisselerinin yüzde 80’ini 2016 yılında İngiltere merkezli BC Partners LLP satın alırken kalan hisseler İsrailli Segol Ailesine aittir.Keter Plastik’in 9’u İsrail’de olmak üzere toplam 20 fabrikası bulunuyor.",
    "documents": [
      "CE"
    ],
    "parent": null,
    "origin": "GB",
    "updated_date": "2024-05-10",
    "domain": "keter.com"
  },
  {
    "company": "Unilever",
    "description": "Unilever, 1930 yılında Margarine Unie ile Lever Brothers şirketlerinin birleşmesiyle kuruldu. 2020 yılında ise Unilever NV ve Unilever PLC birleşti ve Unilever PLC, bütünün ana şirketi oldu.Unilever PLC İngiltere merkezlidir. Yaklaşık 200 ülkede hızlı tüketim ürünleriyle yiyecek ürünleri üreten ve kendi ürünlerini satan firma ayrıca 20’den fazla ülkede kendine ait üretim tesislerine sahiptir.Türkiye’de 1952 yılından beri Unilever San. ve Tic. Türk A.Ş. olarak faaliyet göstermektedir. Şirketin Anadolu, Karadeniz ve Marmara bölgelerinde 8 fabrikası var ve bu fabrikalarda çeşitli yiyecek ve bakım ürünleri üretmektedir.Hissedarları:Wellington Management Group LLP (yüzde 1,34)Morgan Stanley (yüzde 0,35)FMR LLC (yüzde 0,34)Envestnet Asset Management Inc. (yüzde 0,19)Royal Bank of Canada (yüzde 0,15)Lazard Asset Management LLC (yüzde 0,15)American Century Companies Inc. (yüzde 0,14)Federated Hermes Inc. (yüzde 0,1)Northern Trust Corp (yüzde 0,081)Stifel Financial Corp (yüzde 0,08)Natixis Advisors L.P. (yüzde 0,06)JPMorgan Chase & Co. (yüzde 0,056)Truist Financial Corp (yüzde 0,054)LPL Financial LLC (yüzde 0,052)River Road Asset Management LLC (yüzde 0,037)Polen Capital Management LLC (yüzde 0,031)Citigroup Inc. (yüzde 0,027)Advisors Capital Management LLC (yüzde 0,024)Morningstar Investment Services LLC (yüzde 0,024)Hsbc Holdings PLC (yüzde 0,017)Sei Investments Co. (yüzde 0,016)Clark Estates Inc. NY (yüzde 0,016)Becker Capital Management Inc. (yüzde 0,015)Mariner LLC (yüzde 0,015)Scotia Capital Inc. (yüzde 0,013)Ameriprise Financial Inc. (yüzde 0,013)Qube Research & Technologies Ltd (yüzde 0,011)Creative Planning (yüzde 0,01)Modera Wealth Management LLC (yüzde 0,009)iA Global Asset Management Inc. (yüzde 0,009)Townsquare Capital LLC (yüzde 0,008)Lowe Brockenbrough & Co. Inc. (yüzde 0,008)Brandes Investment Partners LP (yüzde 0,008)Envestnet Portfolio Solutions Inc. (yüzde 0,008)Mercer Global Advisors Inc. ADV (yüzde 0,007)Private Advisory Group LLC (yüzde 0,007)Nicholas Company Inc. (yüzde 0,007)Cary Street Partners Investment Advisory LLC (yüzde 0,007)BRYN MAWR TRUST Co (yüzde 0,006)Alerus Financial NA (yüzde 0,006)Guardian Capital LP (yüzde 0,006)Stansberry Asset Management LLC (yüzde 0,005)Clearbridge Investments LLC (yüzde 0,005)Graham Capital Management L.P. (yüzde 0,004)Ancora Advisors LLC (yüzde 0,003)Kayne Anderson Rudnick Investment Management LLC (yüzde 0,003)Invesco Ltd. (yüzde 0,003)Bar Harbor Wealth Management (yüzde 0,002)Trust Co. of Vermont (yüzde 0,002)Deutsche Bank AG (yüzde 0,002)Advisors Asset Management Inc. (yüzde 0,002)Glenmede Trust Co. NA (yüzde 0,002)Logan Capital Management Inc. (yüzde 0,002)O Shaughnessy Asset Management LLC (yüzde 0,002)GSB Wealth Management LLC (yüzde 0,002)Clear Street Markets LLC (yüzde 0,002)Pinkerton Retirement Specialists LLC (yüzde 0,002)B. Riley Wealth Advisors Inc. (yüzde 0,001)Diversified Trust Co (yüzde 0,001)OLD National Bancorp IN (yüzde 0,001)Essex Financial Services Inc. (yüzde 0,001)Penserra Capital Management LLC (yüzde 0,001)Integrated Wealth Concepts LLC (yüzde 0,001)Toroso Investments LLC (yüzde 0,001)Dana Investment Advisors Inc. (yüzde 0,001)Insigneo Advisory Services LLC (yüzde 0,001)Roundview Capital LLC (yüzde 0,001)Synovus Financial Corp (yüzde 0,001)Three Bridge Wealth Advisors LLC (yüzde 0,001)Valley National Advisers Inc. (yüzde 0,001)Weik Capital Management (yüzde 0,001)Mutual Advisors LLC (yüzde 0,001)Cadence Bank (yüzde 0,001)Certified Advisory Corp (yüzde 0,001)River Wealth Advisors LLC (yüzde 0,001)LGL Partners LLC (yüzde 0,001)True Wealth Design LLC (yüzde 0,001)Rodgers Brothers Inc. (yüzde 0,001)Acadian Asset Management LLC (yüzde 0,001)Rathbones Group PLC (yüzde 0,001)Columbia Asset Management (yüzde 0,001)Balentine LLC (yüzde 0,001)Unilever bünyesindeki bazı markalar;AfiyetAkrobatAlacaAlgidaAlgida MaxAmazonArmoniAşçıların MarkasıAşk AteşiAxeAydonduBal BatonBal ÇokoBal ParmakBal-BalBalıkparmakBalkremBallaBalladoBastoncukBecelBelpanBen & Jerry’sBeyazcıkBiskinBizimkiBon CremoBrazilBuz GülüBuz ParmakBuz TabanBuzpembeCalveCarte d’OrCifClearColorsConeCornettoCup RoseÇatapatÇil HorozÇilibiliÇıtı PıtıÇıtırDefineDemreDinazorDiskoDoğalDomestosDoveDove Men+CareDoyumDüelloDüetDüz TabanEkmekmiksEkvatorElidorFan CupFavoriFestivalFinancial CommercialFiyordForzaFruttareFutbolFuturoGitarGoolGökkuşağıHellmann’sİbibikİkizİkramIrmakJetJollyJuice JetsKaktüsKapriKaragözKarbeyazKarelloKedi DiliKesiKeyifKnorrKomik AyakKremiksKremoKup BodrumKutupLa RosaLabambaLalezarLeoLifebuoyLionLiptonLuxMagnumMargaMarifet HanımMayamiksMayaminMeloMeltemNekibukiOmoÖdülPalmelaPenaltıRexonaRinsoRotaSaftadSahraSakızcıkSalsaSalsoSamanyoluSambaSanaSasoSegaSerinSerinceSerinlikSignalSiniSofrabaşıSoftyStarStellaSunlight CifSupraSupraminSürprizSüzümŞakaŞampiyonŞutTini MiniToffyTri BellaTropikTurboUniselUstaların MarkasıÜç TopVazelinVitaVivaVolkanXlXxlYaz BuzYumoşZebraZig Zag",
    "documents": [
      "CE",
      "ISO"
    ],
    "parent": null,
    "origin": "GB",
    "updated_date": "2023-12-11",
    "domain": "unilever.com"
  },
  {
    "company": "Morrisons",
    "description": "Morrisons, 1899 yılında William Morrison tarafından kurulmuş olan Wm Morrison Supermarkets Ltd. bünyesindeki süper market zinciridir.Wm Morrison Supermarkets Ltd. 2021 yılında Amerika merkezli özel sermaye şirketi Clayton, Dubilier & Rice LLC tarafından satın alındı.Bünyesindeki markalar;McColl’sMorrisons DailySafeway",
    "documents": [
      "CE",
      "ISO"
    ],
    "parent": null,
    "origin": "US",
    "updated_date": "2023-05-11",
    "domain": "morrisons.com"
  },
  {
    "company": "Digiturk",
    "description": "Digiturk, 1999 yılında kurulan Krea İçerik Hizmetleri ve Prodüksiyon A.Ş. bünyesindeki dijital televizyon yayıncılığı markasıdır.Yayıncı ve yapımcı kuruluşlardan satın alınan içerikler, ticari paketler halinde abonelerine, bir uydu platform işletmecisi vasıtasıyla ücretli iletmektedir. Ayrıca dergi satışı, film hakları alım ve satımı, prodüksiyon işleri ile reklam hizmetleri vermektedir.Şirket hisselerinin tamamı 2013 yılında Katar merkezli medya grubu Al-Jazeera bünyesindeki beIN Media Group tarafından satın alındı.beIN Media Group’un patronu Nasser Al-Khelaifi aynı zamanda Fransa ekibi Paris Saint Germain(PSG)’nin sahibi.",
    "documents": [
      "CE"
    ],
    "parent": null,
    "origin": "QA",
    "updated_date": "2022-10-02",
    "domain": "digiturk.com.tr"
  }
]